cudnn/__init__.py
cudnn/api_base.py
cudnn/datatypes.py
cudnn/graph.py
cudnn/wrapper.py
cudnn/Release/_compiled_module.cp312-win_amd64.pyd
cudnn/gemm_amax/__init__.py
cudnn/gemm_amax/api.py
cudnn/gemm_amax/dense_blockscaled_gemm_persistent_amax.py
cudnn/gemm_swiglu/__init__.py
cudnn/gemm_swiglu/api.py
cudnn/gemm_swiglu/dense_blockscaled_gemm_persistent_swiglu_interleaved_quant.py
cudnn/gemm_swiglu/dense_gemm_persistent_swiglu.py
cudnn/native_sparse_attention/__init__.py
cudnn/native_sparse_attention/utils.py
cudnn/native_sparse_attention/selection/NSA_select_attn_fwd_hmma.py
cudnn/native_sparse_attention/selection/__init__.py
cudnn/native_sparse_attention/selection/api.py
cudnn/native_sparse_attention/sliding_window_attention/__init__.py
cudnn/native_sparse_attention/sliding_window_attention/api.py
cudnn/native_sparse_attention/top_k/__init__.py
cudnn/native_sparse_attention/top_k/api.py
cudnn/native_sparse_attention/top_k/nsa_top_k_reduction_fwd.py
include/cudnn_backend_base.h
include/cudnn_frontend.h
include/cudnn_frontend_ConvDesc.h
include/cudnn_frontend_Engine.h
include/cudnn_frontend_EngineConfig.h
include/cudnn_frontend_EngineConfigGenerator.h
include/cudnn_frontend_EngineFallbackList.h
include/cudnn_frontend_Errata.h
include/cudnn_frontend_ExecutionPlan.h
include/cudnn_frontend_ExecutionPlanCache.h
include/cudnn_frontend_Filters.h
include/cudnn_frontend_Heuristics.h
include/cudnn_frontend_Logging.h
include/cudnn_frontend_MatMulDesc.h
include/cudnn_frontend_Operation.h
include/cudnn_frontend_OperationGraph.h
include/cudnn_frontend_PointWiseDesc.h
include/cudnn_frontend_ReductionDesc.h
include/cudnn_frontend_Reorder_Tensor.h
include/cudnn_frontend_Resample.h
include/cudnn_frontend_Rng.h
include/cudnn_frontend_Tensor.h
include/cudnn_frontend_VariantPack.h
include/cudnn_frontend_find_plan.h
include/cudnn_frontend_get_plan.h
include/cudnn_frontend_shim.h
include/cudnn_frontend_utils.h
include/cudnn_frontend_version.h
include/cudnn_frontend/context.h
nvidia_cudnn_frontend-1.17.0.dist-info/licenses/LICENSE.txt
nvidia_cudnn_frontend-1.17.0.dist-info/METADATA
nvidia_cudnn_frontend-1.17.0.dist-info/WHEEL
nvidia_cudnn_frontend-1.17.0.dist-info/top_level.txt
nvidia_cudnn_frontend-1.17.0.dist-info/RECORD
