Metadata-Version: 2.4
Name: nvidia-cudnn-frontend
Version: 1.17.0
Summary: CUDNN FrontEnd python library
License: NVIDIA Proprietary Software
Project-URL: Homepage, https://github.com/nvidia/cudnn-frontend
Project-URL: Bug Tracker, https://github.com/nvidia/cudnn-frontend/issues
Classifier: Programming Language :: Python :: 3
Requires-Python: >=3.9
License-File: LICENSE.txt
Provides-Extra: cutedsl
Requires-Dist: nvidia-cutlass-dsl==4.3.1; extra == "cutedsl"
Requires-Dist: cuda-python; extra == "cutedsl"
Requires-Dist: torch; extra == "cutedsl"
Dynamic: license-file
